api_clients/__init__.py
api_clients/apps.py
api_clients/models.py
api_clients/permissions.py
api_clients/serializers.py
api_clients/urls.py
api_clients/views.py
api_clients/migrations/0001_initial.py
api_clients/migrations/__init__.py
api_clients/static/css/api_clients.css
api_clients/static/js/api_clients.js
api_clients/templates/api_clients/base.html
api_clients/utils/__init__.py
api_clients/utils/auth.py
api_clients-0.1.0.dist-info/AUTHORS.rst
api_clients-0.1.0.dist-info/LICENSE
api_clients-0.1.0.dist-info/METADATA
api_clients-0.1.0.dist-info/WHEEL
api_clients-0.1.0.dist-info/top_level.txt
api_clients-0.1.0.dist-info/RECORD
