Metadata-Version: 2.1
Name: api-clients
Version: 0.1.0
Summary: Permission handler for drf API's.
Home-page: https://github.com/jeromecaisip/api_clients
Author: Jerome Caisip
Author-email: jerome.caisip@gmail.com
License: MIT
Keywords: api_clients
Platform: UNKNOWN
Classifier: Development Status :: 3 - Alpha
Classifier: Framework :: Django :: 2.0
Classifier: Intended Audience :: Developers
Classifier: License :: OSI Approved :: BSD License
Classifier: Natural Language :: English
Classifier: Programming Language :: Python :: 2
Classifier: Programming Language :: Python :: 2.7
Classifier: Programming Language :: Python :: 3
Classifier: Programming Language :: Python :: 3.4
Classifier: Programming Language :: Python :: 3.5
Classifier: Programming Language :: Python :: 3.6
Requires-Dist: django-model-utils (>=2.0)
